ExtractWCData/__init__.py
ExtractWCData/_scrape_data.py
ExtractWCData/get_latest_data.py
extract_wc_data-0.0.1.dist-info/METADATA
extract_wc_data-0.0.1.dist-info/WHEEL
extract_wc_data-0.0.1.dist-info/top_level.txt
extract_wc_data-0.0.1.dist-info/RECORD
